<?xml version="1.0"?>
<VMAF version="1.5.3">
	<params model="vmaf_v0.6.1.pkl" scaledWidth="768" scaledHeight="432" subsample="1" num_bootstrap_models="0" bootstrap_model_list_str="" />
	<fyi numOfFrames="250" aggregateVMAF="65.9265" aggregatePSNR="32.909" aggregateSSIM="0.917679" aggregateMS_SSIM="0.953075" execFps="40.5069" timeTaken="6.17179" />
	<frames>
		<frame frameNum="0" adm2="0.940214" motion2="0" ms_ssim="0.983758" psnr="36.8364" ssim="0.970353" vif_scale0="0.528634" vif_scale1="0.816632" vif_scale2="0.889083" vif_scale3="0.928985" vmaf="74.5991" />
		<frame frameNum="1" adm2="0.93071" motion2="10.409" ms_ssim="0.98013" psnr="35.8879" ssim="0.964833" vif_scale0="0.50026" vif_scale1="0.784556" vif_scale2="0.860985" vif_scale3="0.905123" vmaf="81.6597" />
		<frame frameNum="2" adm2="0.915899" motion2="10.0665" ms_ssim="0.974896" psnr="35.0364" ssim="0.956242" vif_scale0="0.46819" vif_scale1="0.745408" vif_scale2="0.828799" vif_scale3="0.881032" vmaf="75.4941" />
		<frame frameNum="3" adm2="0.905358" motion2="9.91723" ms_ssim="0.967702" psnr="34.0835" ssim="0.945663" vif_scale0="0.438568" vif_scale1="0.703299" vif_scale2="0.789765" vif_scale3="0.847999" vmaf="69.8408" />
		<frame frameNum="4" adm2="0.887612" motion2="9.91723" ms_ssim="0.958108" psnr="33.0292" ssim="0.932099" vif_scale0="0.405477" vif_scale1="0.657378" vif_scale2="0.746401" vif_scale3="0.810602" vmaf="62.8935" />
		<frame frameNum="5" adm2="0.884226" motion2="10.1601" ms_ssim="0.957194" psnr="32.7193" ssim="0.92963" vif_scale0="0.394851" vif_scale1="0.647602" vif_scale2="0.738834" vif_scale3="0.807355" vmaf="62.1615" />
		<frame frameNum="6" adm2="0.881191" motion2="9.98636" ms_ssim="0.954815" psnr="32.4332" ssim="0.924374" vif_scale0="0.38482" vif_scale1="0.640569" vif_scale2="0.734899" vif_scale3="0.805043" vmaf="61.2293" />
		<frame frameNum="7" adm2="0.869468" motion2="9.73525" ms_ssim="0.949467" psnr="31.9106" ssim="0.917382" vif_scale0="0.366449" vif_scale1="0.614134" vif_scale2="0.709013" vif_scale3="0.781797" vmaf="56.8785" />
		<frame frameNum="8" adm2="0.861375" motion2="9.35245" ms_ssim="0.94433" psnr="31.7308" ssim="0.90917" vif_scale0="0.354525" vif_scale1="0.59828" vif_scale2="0.694657" vif_scale3="0.766405" vmaf="53.8812" />
		<frame frameNum="9" adm2="0.854395" motion2="8.15964" ms_ssim="0.94061" psnr="31.4048" ssim="0.903354" vif_scale0="0.344612" vif_scale1="0.588309" vif_scale2="0.685259" vif_scale3="0.759271" vmaf="50.8988" />
		<frame frameNum="10" adm2="0.857153" motion2="7.96229" ms_ssim="0.937703" psnr="31.2346" ssim="0.898104" vif_scale0="0.336157" vif_scale1="0.58355" vif_scale2="0.684825" vif_scale3="0.760871" vmaf="51.4148" />
		<frame frameNum="11" adm2="0.855041" motion2="7.82884" ms_ssim="0.931079" psnr="30.7435" ssim="0.888384" vif_scale0="0.322856" vif_scale1="0.565032" vif_scale2="0.664114" vif_scale3="0.739965" vmaf="49.5036" />
		<frame frameNum="12" adm2="0.856124" motion2="7.82884" ms_ssim="0.934779" psnr="31.0286" ssim="0.892946" vif_scale0="0.329337" vif_scale1="0.576238" vif_scale2="0.676712" vif_scale3="0.753064" vmaf="50.5666" />
		<frame frameNum="13" adm2="0.854922" motion2="7.92744" ms_ssim="0.935632" psnr="31.0351" ssim="0.894236" vif_scale0="0.329116" vif_scale1="0.580248" vif_scale2="0.681474" vif_scale3="0.758088" vmaf="50.7908" />
		<frame frameNum="14" adm2="0.860944" motion2="8.05968" ms_ssim="0.933394" psnr="30.977" ssim="0.890348" vif_scale0="0.323946" vif_scale1="0.575829" vif_scale2="0.677041" vif_scale3="0.753439" vmaf="51.7561" />
		<frame frameNum="15" adm2="0.85294" motion2="8.22372" ms_ssim="0.932727" psnr="30.8493" ssim="0.888949" vif_scale0="0.318723" vif_scale1="0.571225" vif_scale2="0.674243" vif_scale3="0.753351" vmaf="50.4384" />
		<frame frameNum="16" adm2="0.928635" motion2="8.30132" ms_ssim="0.974307" psnr="34.5714" ssim="0.952442" vif_scale0="0.443773" vif_scale1="0.773796" vif_scale2="0.863404" vif_scale3="0.912696" vmaf="79.7349" />
		<frame frameNum="17" adm2="0.91854" motion2="8.42479" ms_ssim="0.969941" psnr="34.007" ssim="0.946465" vif_scale0="0.426711" vif_scale1="0.740666" vif_scale2="0.832892" vif_scale3="0.885379" vmaf="74.854" />
		<frame frameNum="18" adm2="0.898834" motion2="8.84198" ms_ssim="0.963663" psnr="33.3129" ssim="0.937063" vif_scale0="0.403439" vif_scale1="0.70072" vif_scale2="0.795476" vif_scale3="0.853558" vmaf="68.0687" />
		<frame frameNum="19" adm2="0.887021" motion2="9.23375" ms_ssim="0.955083" psnr="32.568" ssim="0.924248" vif_scale0="0.378423" vif_scale1="0.655289" vif_scale2="0.749339" vif_scale3="0.812101" vmaf="62.353" />
		<frame frameNum="20" adm2="0.874375" motion2="9.52144" ms_ssim="0.948815" psnr="32.0021" ssim="0.91599" vif_scale0="0.361508" vif_scale1="0.625816" vif_scale2="0.718945" vif_scale3="0.784639" vmaf="57.9219" />
		<frame frameNum="21" adm2="0.869549" motion2="9.7404" ms_ssim="0.944831" psnr="31.8505" ssim="0.911106" vif_scale0="0.354617" vif_scale1="0.606582" vif_scale2="0.70002" vif_scale3="0.767358" vmaf="55.8997" />
		<frame frameNum="22" adm2="0.857813" motion2="10.2547" ms_ssim="0.944671" psnr="31.9463" ssim="0.910793" vif_scale0="0.35467" vif_scale1="0.60475" vif_scale2="0.698848" vif_scale3="0.768059" vmaf="54.2034" />
		<frame frameNum="23" adm2="0.859135" motion2="10.7577" ms_ssim="0.945128" psnr="31.9036" ssim="0.910545" vif_scale0="0.356428" vif_scale1="0.602318" vif_scale2="0.698517" vif_scale3="0.767764" vmaf="54.9474" />
		<frame frameNum="24" adm2="0.851928" motion2="11.1752" ms_ssim="0.937284" psnr="31.4142" ssim="0.89889" vif_scale0="0.339574" vif_scale1="0.576173" vif_scale2="0.672071" vif_scale3="0.74556" vmaf="52.4347" />
		<frame frameNum="25" adm2="0.843563" motion2="10.8911" ms_ssim="0.935215" psnr="31.2973" ssim="0.896359" vif_scale0="0.333852" vif_scale1="0.567405" vif_scale2="0.665224" vif_scale3="0.739896" vmaf="50.2698" />
		<frame frameNum="26" adm2="0.847053" motion2="10.8911" ms_ssim="0.93229" psnr="31.3032" ssim="0.893259" vif_scale0="0.332255" vif_scale1="0.56245" vif_scale2="0.659477" vif_scale3="0.735539" vmaf="50.6192" />
		<frame frameNum="27" adm2="0.839939" motion2="11.3788" ms_ssim="0.931819" psnr="31.3215" ssim="0.892805" vif_scale0="0.327512" vif_scale1="0.557912" vif_scale2="0.655391" vif_scale3="0.729369" vmaf="49.4107" />
		<frame frameNum="28" adm2="0.841574" motion2="10.6715" ms_ssim="0.931183" psnr="31.2873" ssim="0.89051" vif_scale0="0.325472" vif_scale1="0.557738" vif_scale2="0.658043" vif_scale3="0.735374" vmaf="49.4549" />
		<frame frameNum="29" adm2="0.836036" motion2="10.6715" ms_ssim="0.930391" psnr="31.1173" ssim="0.888193" vif_scale0="0.319098" vif_scale1="0.549303" vif_scale2="0.650592" vif_scale3="0.73147" vmaf="48.2141" />
		<frame frameNum="30" adm2="0.834387" motion2="10.6796" ms_ssim="0.928613" psnr="30.9964" ssim="0.886316" vif_scale0="0.313323" vif_scale1="0.539377" vif_scale2="0.640325" vif_scale3="0.718802" vmaf="47.1828" />
		<frame frameNum="31" adm2="0.830786" motion2="10.7681" ms_ssim="0.915822" psnr="30.3785" ssim="0.871054" vif_scale0="0.294509" vif_scale1="0.503474" vif_scale2="0.598608" vif_scale3="0.678185" vmaf="44.373" />
		<frame frameNum="32" adm2="0.91267" motion2="10.7681" ms_ssim="0.968023" psnr="34.4564" ssim="0.943076" vif_scale0="0.421552" vif_scale1="0.71575" vif_scale2="0.813892" vif_scale3="0.87462" vmaf="74.7842" />
		<frame frameNum="33" adm2="0.90444" motion2="10.6388" ms_ssim="0.962599" psnr="33.6538" ssim="0.934748" vif_scale0="0.398746" vif_scale1="0.680265" vif_scale2="0.779095" vif_scale3="0.845398" vmaf="70.097" />
		<frame frameNum="34" adm2="0.884465" motion2="9.96598" ms_ssim="0.956205" psnr="32.944" ssim="0.925899" vif_scale0="0.375978" vif_scale1="0.647515" vif_scale2="0.746259" vif_scale3="0.814657" vmaf="62.7495" />
		<frame frameNum="35" adm2="0.886211" motion2="9.41535" ms_ssim="0.956898" psnr="33.0823" ssim="0.926161" vif_scale0="0.379662" vif_scale1="0.65465" vif_scale2="0.755449" vif_scale3="0.826186" vmaf="63.4946" />
		<frame frameNum="36" adm2="0.875881" motion2="8.92246" ms_ssim="0.947824" psnr="32.224" ssim="0.912271" vif_scale0="0.350029" vif_scale1="0.613417" vif_scale2="0.715729" vif_scale3="0.789256" vmaf="58.0162" />
		<frame frameNum="37" adm2="0.881992" motion2="8.52195" ms_ssim="0.948627" psnr="32.5519" ssim="0.912655" vif_scale0="0.351299" vif_scale1="0.627955" vif_scale2="0.735708" vif_scale3="0.8074" vmaf="60.335" />
		<frame frameNum="38" adm2="0.8661" motion2="8.52195" ms_ssim="0.939073" psnr="31.8313" ssim="0.897999" vif_scale0="0.325472" vif_scale1="0.588821" vif_scale2="0.695946" vif_scale3="0.774129" vmaf="54.7051" />
		<frame frameNum="39" adm2="0.885897" motion2="8.56453" ms_ssim="0.944755" psnr="32.2675" ssim="0.905007" vif_scale0="0.337955" vif_scale1="0.617041" vif_scale2="0.72872" vif_scale3="0.806067" vmaf="61.0261" />
		<frame frameNum="40" adm2="0.869804" motion2="9.19919" ms_ssim="0.936657" psnr="31.5343" ssim="0.89183" vif_scale0="0.316954" vif_scale1="0.581559" vif_scale2="0.69064" vif_scale3="0.770419" vmaf="55.8427" />
		<frame frameNum="41" adm2="0.871333" motion2="9.62841" ms_ssim="0.937416" psnr="31.4282" ssim="0.891496" vif_scale0="0.318524" vif_scale1="0.593332" vif_scale2="0.707112" vif_scale3="0.787862" vmaf="57.883" />
		<frame frameNum="42" adm2="0.863714" motion2="9.12169" ms_ssim="0.931332" psnr="30.719" ssim="0.882688" vif_scale0="0.300042" vif_scale1="0.570093" vif_scale2="0.683827" vif_scale3="0.768063" vmaf="54.536" />
		<frame frameNum="43" adm2="0.87275" motion2="8.67058" ms_ssim="0.935195" psnr="31.1102" ssim="0.88824" vif_scale0="0.309559" vif_scale1="0.59567" vif_scale2="0.713101" vif_scale3="0.79424" vmaf="57.7815" />
		<frame frameNum="44" adm2="0.865215" motion2="7.55813" ms_ssim="0.929735" psnr="30.788" ssim="0.880186" vif_scale0="0.301532" vif_scale1="0.57927" vif_scale2="0.696167" vif_scale3="0.780582" vmaf="54.2318" />
		<frame frameNum="45" adm2="0.871109" motion2="7.06098" ms_ssim="0.934614" psnr="31.233" ssim="0.886927" vif_scale0="0.311072" vif_scale1="0.601764" vif_scale2="0.721123" vif_scale3="0.803334" vmaf="56.5859" />
		<frame frameNum="46" adm2="0.870108" motion2="7.06098" ms_ssim="0.934597" psnr="31.3338" ssim="0.887464" vif_scale0="0.311564" vif_scale1="0.605202" vif_scale2="0.724233" vif_scale3="0.805329" vmaf="56.5574" />
		<frame frameNum="47" adm2="0.886171" motion2="6.63618" ms_ssim="0.945644" psnr="32.2584" ssim="0.904299" vif_scale0="0.341701" vif_scale1="0.656107" vif_scale2="0.772387" vif_scale3="0.845779" vmaf="62.5956" />
		<frame frameNum="48" adm2="0.910363" motion2="6.4656" ms_ssim="0.959787" psnr="33.3393" ssim="0.927349" vif_scale0="0.375424" vif_scale1="0.716055" vif_scale2="0.823052" vif_scale3="0.882719" vmaf="70.8567" />
		<frame frameNum="49" adm2="0.901302" motion2="6.03556" ms_ssim="0.954951" psnr="32.9276" ssim="0.920665" vif_scale0="0.356931" vif_scale1="0.689189" vif_scale2="0.796642" vif_scale3="0.861291" vmaf="66.4486" />
		<frame frameNum="50" adm2="0.901426" motion2="5.74045" ms_ssim="0.954536" psnr="32.9628" ssim="0.918915" vif_scale0="0.351563" vif_scale1="0.687756" vif_scale2="0.797295" vif_scale3="0.860903" vmaf="66.19" />
		<frame frameNum="51" adm2="0.901063" motion2="5.74045" ms_ssim="0.955135" psnr="33.0218" ssim="0.920356" vif_scale0="0.356029" vif_scale1="0.689693" vif_scale2="0.798706" vif_scale3="0.86381" vmaf="66.3337" />
		<frame frameNum="52" adm2="0.900524" motion2="5.75088" ms_ssim="0.957269" psnr="33.1699" ssim="0.923857" vif_scale0="0.365586" vif_scale1="0.707978" vif_scale2="0.816032" vif_scale3="0.876947" vmaf="67.5546" />
		<frame frameNum="53" adm2="0.895577" motion2="5.54319" ms_ssim="0.955459" psnr="32.9801" ssim="0.921014" vif_scale0="0.357445" vif_scale1="0.696153" vif_scale2="0.804739" vif_scale3="0.868046" vmaf="65.463" />
		<frame frameNum="54" adm2="0.905223" motion2="5.17674" ms_ssim="0.959291" psnr="33.4854" ssim="0.927554" vif_scale0="0.374605" vif_scale1="0.721689" vif_scale2="0.827746" vif_scale3="0.887098" vmaf="68.8869" />
		<frame frameNum="55" adm2="0.898909" motion2="4.8467" ms_ssim="0.956104" psnr="33.142" ssim="0.921879" vif_scale0="0.359445" vif_scale1="0.700282" vif_scale2="0.80815" vif_scale3="0.872078" vmaf="65.7492" />
		<frame frameNum="56" adm2="0.90725" motion2="4.8467" ms_ssim="0.958777" psnr="33.4449" ssim="0.926145" vif_scale0="0.37205" vif_scale1="0.7214" vif_scale2="0.827128" vif_scale3="0.886643" vmaf="68.9007" />
		<frame frameNum="57" adm2="0.904349" motion2="4.6271" ms_ssim="0.955923" psnr="33.0935" ssim="0.92151" vif_scale0="0.358776" vif_scale1="0.699512" vif_scale2="0.806991" vif_scale3="0.870091" vmaf="66.4378" />
		<frame frameNum="58" adm2="0.908456" motion2="4.46226" ms_ssim="0.95841" psnr="33.4065" ssim="0.925741" vif_scale0="0.370008" vif_scale1="0.721982" vif_scale2="0.82761" vif_scale3="0.887184" vmaf="68.7904" />
		<frame frameNum="59" adm2="0.908003" motion2="4.3597" ms_ssim="0.957981" psnr="33.3838" ssim="0.92517" vif_scale0="0.367397" vif_scale1="0.721079" vif_scale2="0.826577" vif_scale3="0.886023" vmaf="68.4852" />
		<frame frameNum="60" adm2="0.910847" motion2="4.29325" ms_ssim="0.961337" psnr="33.6932" ssim="0.930103" vif_scale0="0.37822" vif_scale1="0.740445" vif_scale2="0.843586" vif_scale3="0.900102" vmaf="70.4367" />
		<frame frameNum="61" adm2="0.905602" motion2="4.08954" ms_ssim="0.958854" psnr="33.447" ssim="0.926692" vif_scale0="0.36829" vif_scale1="0.723353" vif_scale2="0.828541" vif_scale3="0.886716" vmaf="67.8074" />
		<frame frameNum="62" adm2="0.916694" motion2="4.05273" ms_ssim="0.960753" psnr="33.6697" ssim="0.929713" vif_scale0="0.378141" vif_scale1="0.738743" vif_scale2="0.840531" vif_scale3="0.897063" vmaf="71.0478" />
		<frame frameNum="63" adm2="0.910775" motion2="4.05273" ms_ssim="0.958398" psnr="33.3538" ssim="0.925515" vif_scale0="0.366622" vif_scale1="0.72071" vif_scale2="0.824092" vif_scale3="0.881291" vmaf="68.2972" />
		<frame frameNum="64" adm2="0.928076" motion2="4.09716" ms_ssim="0.96545" psnr="34.1457" ssim="0.937204" vif_scale0="0.392987" vif_scale1="0.758941" vif_scale2="0.857388" vif_scale3="0.910209" vmaf="74.8393" />
		<frame frameNum="65" adm2="0.923084" motion2="4.2066" ms_ssim="0.962884" psnr="33.8195" ssim="0.933229" vif_scale0="0.384654" vif_scale1="0.743199" vif_scale2="0.842834" vif_scale3="0.898041" vmaf="72.6256" />
		<frame frameNum="66" adm2="0.927325" motion2="4.43382" ms_ssim="0.963705" psnr="33.8878" ssim="0.934222" vif_scale0="0.386698" vif_scale1="0.750663" vif_scale2="0.850414" vif_scale3="0.904992" vmaf="74.4767" />
		<frame frameNum="67" adm2="0.921014" motion2="4.61228" ms_ssim="0.961472" psnr="33.5936" ssim="0.930351" vif_scale0="0.375637" vif_scale1="0.736735" vif_scale2="0.839812" vif_scale3="0.897632" vmaf="72.5724" />
		<frame frameNum="68" adm2="0.920415" motion2="4.69207" ms_ssim="0.960599" psnr="33.533" ssim="0.929101" vif_scale0="0.372889" vif_scale1="0.735103" vif_scale2="0.838121" vif_scale3="0.895094" vmaf="72.3107" />
		<frame frameNum="69" adm2="0.92116" motion2="4.4561" ms_ssim="0.961258" psnr="33.6875" ssim="0.930271" vif_scale0="0.375115" vif_scale1="0.7401" vif_scale2="0.842423" vif_scale3="0.898597" vmaf="72.5779" />
		<frame frameNum="70" adm2="0.913232" motion2="4.20258" ms_ssim="0.958229" psnr="33.4163" ssim="0.925552" vif_scale0="0.362614" vif_scale1="0.722214" vif_scale2="0.826606" vif_scale3="0.885612" vmaf="69.355" />
		<frame frameNum="71" adm2="0.917211" motion2="3.93877" ms_ssim="0.959671" psnr="33.6707" ssim="0.927758" vif_scale0="0.367883" vif_scale1="0.736539" vif_scale2="0.840573" vif_scale3="0.897003" vmaf="71.0752" />
		<frame frameNum="72" adm2="0.916017" motion2="3.78445" ms_ssim="0.958835" psnr="33.5713" ssim="0.925821" vif_scale0="0.36459" vif_scale1="0.733988" vif_scale2="0.840039" vif_scale3="0.899554" vmaf="70.8584" />
		<frame frameNum="73" adm2="0.920967" motion2="3.78445" ms_ssim="0.959008" psnr="33.5286" ssim="0.926019" vif_scale0="0.364684" vif_scale1="0.734868" vif_scale2="0.841543" vif_scale3="0.900338" vmaf="71.9707" />
		<frame frameNum="74" adm2="0.919163" motion2="3.89275" ms_ssim="0.958453" psnr="33.4523" ssim="0.925022" vif_scale0="0.363601" vif_scale1="0.731854" vif_scale2="0.839344" vif_scale3="0.898801" vmaf="71.5537" />
		<frame frameNum="75" adm2="0.920513" motion2="4.18165" ms_ssim="0.958784" psnr="33.4434" ssim="0.925566" vif_scale0="0.366406" vif_scale1="0.732018" vif_scale2="0.838627" vif_scale3="0.89793" vmaf="72.0425" />
		<frame frameNum="76" adm2="0.923155" motion2="4.77536" ms_ssim="0.95909" psnr="33.4299" ssim="0.925787" vif_scale0="0.367961" vif_scale1="0.734409" vif_scale2="0.841001" vif_scale3="0.900202" vmaf="73.453" />
		<frame frameNum="77" adm2="0.921673" motion2="5.14446" ms_ssim="0.95825" psnr="33.2749" ssim="0.924337" vif_scale0="0.363735" vif_scale1="0.72624" vif_scale2="0.833284" vif_scale3="0.893587" vmaf="72.8573" />
		<frame frameNum="78" adm2="0.915494" motion2="5.3404" ms_ssim="0.957152" psnr="33.1305" ssim="0.922816" vif_scale0="0.359541" vif_scale1="0.71506" vif_scale2="0.822337" vif_scale3="0.883844" vmaf="70.8171" />
		<frame frameNum="79" adm2="0.908319" motion2="5.48467" ms_ssim="0.954625" psnr="32.8631" ssim="0.918786" vif_scale0="0.351727" vif_scale1="0.700335" vif_scale2="0.808357" vif_scale3="0.87179" vmaf="68.3263" />
		<frame frameNum="80" adm2="0.937683" motion2="5.18535" ms_ssim="0.972316" psnr="34.8305" ssim="0.948329" vif_scale0="0.428809" vif_scale1="0.811135" vif_scale2="0.898256" vif_scale3="0.938278" vmaf="81.4098" />
		<frame frameNum="81" adm2="0.933187" motion2="5.18535" ms_ssim="0.970313" psnr="34.4501" ssim="0.945032" vif_scale0="0.416858" vif_scale1="0.795492" vif_scale2="0.88471" vif_scale3="0.927691" vmaf="79.2136" />
		<frame frameNum="82" adm2="0.924825" motion2="5.25268" ms_ssim="0.967239" psnr="34.0506" ssim="0.939749" vif_scale0="0.401777" vif_scale1="0.774809" vif_scale2="0.868182" vif_scale3="0.916026" vmaf="76.1673" />
		<frame frameNum="83" adm2="0.920052" motion2="5.53037" ms_ssim="0.963982" psnr="33.4111" ssim="0.934238" vif_scale0="0.387825" vif_scale1="0.748643" vif_scale2="0.844839" vif_scale3="0.895801" vmaf="73.3082" />
		<frame frameNum="84" adm2="0.912073" motion2="5.70686" ms_ssim="0.95971" psnr="32.8043" ssim="0.927095" vif_scale0="0.374794" vif_scale1="0.721608" vif_scale2="0.818371" vif_scale3="0.875047" vmaf="69.6561" />
		<frame frameNum="85" adm2="0.90342" motion2="5.42644" ms_ssim="0.954962" psnr="32.3694" ssim="0.920266" vif_scale0="0.364127" vif_scale1="0.700903" vif_scale2="0.795913" vif_scale3="0.854314" vmaf="65.6005" />
		<frame frameNum="86" adm2="0.910056" motion2="5.42644" ms_ssim="0.959025" psnr="32.7884" ssim="0.9264" vif_scale0="0.371761" vif_scale1="0.71938" vif_scale2="0.817469" vif_scale3="0.874325" vmaf="68.8926" />
		<frame frameNum="87" adm2="0.899191" motion2="5.50527" ms_ssim="0.952433" psnr="32.0613" ssim="0.916007" vif_scale0="0.351845" vif_scale1="0.681966" vif_scale2="0.780145" vif_scale3="0.841009" vmaf="63.6286" />
		<frame frameNum="88" adm2="0.900635" motion2="5.50527" ms_ssim="0.953545" psnr="32.0749" ssim="0.917489" vif_scale0="0.3521" vif_scale1="0.685168" vif_scale2="0.784976" vif_scale3="0.845358" vmaf="64.3362" />
		<frame frameNum="89" adm2="0.894317" motion2="5.84729" ms_ssim="0.950754" psnr="31.9849" ssim="0.913368" vif_scale0="0.34736" vif_scale1="0.678321" vif_scale2="0.779152" vif_scale3="0.838108" vmaf="62.8394" />
		<frame frameNum="90" adm2="0.897353" motion2="6.1806" ms_ssim="0.947756" psnr="31.8281" ssim="0.908433" vif_scale0="0.340086" vif_scale1="0.66511" vif_scale2="0.767834" vif_scale3="0.831611" vmaf="63.1515" />
		<frame frameNum="91" adm2="0.895314" motion2="6.57167" ms_ssim="0.946125" psnr="31.8677" ssim="0.905712" vif_scale0="0.337899" vif_scale1="0.664155" vif_scale2="0.768533" vif_scale3="0.834082" vmaf="63.3556" />
		<frame frameNum="92" adm2="0.879849" motion2="6.1788" ms_ssim="0.93754" psnr="31.322" ssim="0.894956" vif_scale0="0.317257" vif_scale1="0.631499" vif_scale2="0.736642" vif_scale3="0.80496" vmaf="57.5086" />
		<frame frameNum="93" adm2="0.880221" motion2="5.98519" ms_ssim="0.933697" psnr="31.1945" ssim="0.888421" vif_scale0="0.310998" vif_scale1="0.619923" vif_scale2="0.724499" vif_scale3="0.795854" vmaf="56.6345" />
		<frame frameNum="94" adm2="0.875843" motion2="5.98519" ms_ssim="0.935884" psnr="31.5266" ssim="0.89165" vif_scale0="0.31614" vif_scale1="0.632395" vif_scale2="0.739014" vif_scale3="0.809352" vmaf="56.8827" />
		<frame frameNum="95" adm2="0.872759" motion2="6.0906" ms_ssim="0.933223" psnr="31.4203" ssim="0.888619" vif_scale0="0.312991" vif_scale1="0.622892" vif_scale2="0.728551" vif_scale3="0.799395" vmaf="55.5945" />
		<frame frameNum="96" adm2="0.92833" motion2="6.47319" ms_ssim="0.963624" psnr="33.6489" ssim="0.931929" vif_scale0="0.378797" vif_scale1="0.757981" vif_scale2="0.859877" vif_scale3="0.915275" vmaf="77.9703" />
		<frame frameNum="97" adm2="0.918374" motion2="6.3368" ms_ssim="0.960124" psnr="33.3016" ssim="0.926788" vif_scale0="0.368289" vif_scale1="0.735567" vif_scale2="0.839598" vif_scale3="0.900233" vmaf="74.0863" />
		<frame frameNum="98" adm2="0.911273" motion2="6.3368" ms_ssim="0.955388" psnr="32.7458" ssim="0.918833" vif_scale0="0.352022" vif_scale1="0.708568" vif_scale2="0.814177" vif_scale3="0.876532" vmaf="70.2827" />
		<frame frameNum="99" adm2="0.894177" motion2="6.57525" ms_ssim="0.951823" psnr="32.2326" ssim="0.912621" vif_scale0="0.340618" vif_scale1="0.687178" vif_scale2="0.795612" vif_scale3="0.862693" vmaf="65.7197" />
		<frame frameNum="100" adm2="0.891896" motion2="6.52123" ms_ssim="0.949852" psnr="32.0834" ssim="0.909436" vif_scale0="0.336298" vif_scale1="0.6801" vif_scale2="0.788886" vif_scale3="0.857929" vmaf="64.7423" />
		<frame frameNum="101" adm2="0.880133" motion2="6.17852" ms_ssim="0.943318" psnr="31.483" ssim="0.900209" vif_scale0="0.318289" vif_scale1="0.646431" vif_scale2="0.753613" vif_scale3="0.825655" vmaf="59.2256" />
		<frame frameNum="102" adm2="0.884031" motion2="6.17852" ms_ssim="0.945478" psnr="31.8565" ssim="0.902828" vif_scale0="0.321558" vif_scale1="0.660656" vif_scale2="0.772226" vif_scale3="0.843082" vmaf="61.5461" />
		<frame frameNum="103" adm2="0.870253" motion2="6.25169" ms_ssim="0.93877" psnr="31.3538" ssim="0.893322" vif_scale0="0.301335" vif_scale1="0.62991" vif_scale2="0.741617" vif_scale3="0.817971" vmaf="56.8006" />
		<frame frameNum="104" adm2="0.883813" motion2="5.73231" ms_ssim="0.943474" psnr="31.8894" ssim="0.900725" vif_scale0="0.315313" vif_scale1="0.660026" vif_scale2="0.7708" vif_scale3="0.841573" vmaf="60.9335" />
		<frame frameNum="105" adm2="0.872358" motion2="5.55742" ms_ssim="0.936437" psnr="31.3073" ssim="0.889875" vif_scale0="0.296574" vif_scale1="0.627677" vif_scale2="0.738765" vif_scale3="0.813582" vmaf="56.1928" />
		<frame frameNum="106" adm2="0.882174" motion2="5.21864" ms_ssim="0.940552" psnr="31.7137" ssim="0.895334" vif_scale0="0.305611" vif_scale1="0.650931" vif_scale2="0.765645" vif_scale3="0.838024" vmaf="59.8331" />
		<frame frameNum="107" adm2="0.87391" motion2="4.77598" ms_ssim="0.9351" psnr="31.1482" ssim="0.887156" vif_scale0="0.291334" vif_scale1="0.623168" vif_scale2="0.737698" vif_scale3="0.813237" vmaf="55.7347" />
		<frame frameNum="108" adm2="0.880114" motion2="4.62667" ms_ssim="0.940649" psnr="31.4949" ssim="0.894678" vif_scale0="0.304668" vif_scale1="0.645978" vif_scale2="0.76178" vif_scale3="0.836474" vmaf="58.6662" />
		<frame frameNum="109" adm2="0.880151" motion2="4.62667" ms_ssim="0.939786" psnr="31.3601" ssim="0.893132" vif_scale0="0.303379" vif_scale1="0.642693" vif_scale2="0.759179" vif_scale3="0.835519" vmaf="58.5762" />
		<frame frameNum="110" adm2="0.889075" motion2="4.62838" ms_ssim="0.943472" psnr="31.6889" ssim="0.899141" vif_scale0="0.318757" vif_scale1="0.661196" vif_scale2="0.774702" vif_scale3="0.846753" vmaf="61.2749" />
		<frame frameNum="111" adm2="0.878809" motion2="4.62838" ms_ssim="0.938548" psnr="31.2498" ssim="0.892095" vif_scale0="0.306239" vif_scale1="0.634406" vif_scale2="0.747531" vif_scale3="0.821439" vmaf="57.1308" />
		<frame frameNum="112" adm2="0.915994" motion2="4.85935" ms_ssim="0.956065" psnr="32.6875" ssim="0.919903" vif_scale0="0.356097" vif_scale1="0.723232" vif_scale2="0.833437" vif_scale3="0.896712" vmaf="71.6718" />
		<frame frameNum="113" adm2="0.910807" motion2="5.2094" ms_ssim="0.954352" psnr="32.4035" ssim="0.917386" vif_scale0="0.348923" vif_scale1="0.707362" vif_scale2="0.817576" vif_scale3="0.882094" vmaf="69.5331" />
		<frame frameNum="114" adm2="0.904802" motion2="5.21166" ms_ssim="0.951394" psnr="32.1258" ssim="0.912592" vif_scale0="0.338051" vif_scale1="0.687141" vif_scale2="0.799334" vif_scale3="0.866712" vmaf="66.8363" />
		<frame frameNum="115" adm2="0.900175" motion2="5.01365" ms_ssim="0.94943" psnr="32.0352" ssim="0.909277" vif_scale0="0.332925" vif_scale1="0.677798" vif_scale2="0.791018" vif_scale3="0.859494" vmaf="65.0372" />
		<frame frameNum="116" adm2="0.903265" motion2="5.01365" ms_ssim="0.95004" psnr="32.268" ssim="0.910119" vif_scale0="0.336929" vif_scale1="0.686296" vif_scale2="0.799993" vif_scale3="0.866495" vmaf="66.3395" />
		<frame frameNum="117" adm2="0.897152" motion2="5.18434" ms_ssim="0.945196" psnr="31.8367" ssim="0.902624" vif_scale0="0.323597" vif_scale1="0.661999" vif_scale2="0.774885" vif_scale3="0.843739" vmaf="63.2156" />
		<frame frameNum="118" adm2="0.903219" motion2="5.35993" ms_ssim="0.949358" psnr="32.2861" ssim="0.909152" vif_scale0="0.33779" vif_scale1="0.685476" vif_scale2="0.7985" vif_scale3="0.864906" vmaf="66.5372" />
		<frame frameNum="119" adm2="0.898357" motion2="5.51447" ms_ssim="0.945652" psnr="31.9278" ssim="0.902812" vif_scale0="0.324117" vif_scale1="0.662868" vif_scale2="0.777212" vif_scale3="0.848757" vmaf="64.1987" />
		<frame frameNum="120" adm2="0.907722" motion2="5.50856" ms_ssim="0.951777" psnr="32.4712" ssim="0.91292" vif_scale0="0.343937" vif_scale1="0.697042" vif_scale2="0.807647" vif_scale3="0.871509" vmaf="68.241" />
		<frame frameNum="121" adm2="0.900335" motion2="5.50856" ms_ssim="0.946606" psnr="32.0439" ssim="0.905145" vif_scale0="0.327243" vif_scale1="0.665713" vif_scale2="0.776226" vif_scale3="0.84408" vmaf="64.1942" />
		<frame frameNum="122" adm2="0.900776" motion2="5.31536" ms_ssim="0.948696" psnr="32.2395" ssim="0.908624" vif_scale0="0.333568" vif_scale1="0.679666" vif_scale2="0.79119" vif_scale3="0.859785" vmaf="65.4776" />
		<frame frameNum="123" adm2="0.893594" motion2="5.31536" ms_ssim="0.942907" psnr="31.7523" ssim="0.899875" vif_scale0="0.313859" vif_scale1="0.648876" vif_scale2="0.7618" vif_scale3="0.83798" vmaf="62.0371" />
		<frame frameNum="124" adm2="0.900364" motion2="5.44045" ms_ssim="0.947363" psnr="32.1579" ssim="0.906784" vif_scale0="0.328286" vif_scale1="0.677908" vif_scale2="0.791656" vif_scale3="0.860805" vmaf="65.6474" />
		<frame frameNum="125" adm2="0.891735" motion2="5.97463" ms_ssim="0.942219" psnr="31.7882" ssim="0.899866" vif_scale0="0.316638" vif_scale1="0.652706" vif_scale2="0.765606" vif_scale3="0.839907" vmaf="62.5394" />
		<frame frameNum="126" adm2="0.90221" motion2="6.18432" ms_ssim="0.946864" psnr="32.1723" ssim="0.905126" vif_scale0="0.330227" vif_scale1="0.676626" vif_scale2="0.789678" vif_scale3="0.861703" vmaf="66.7883" />
		<frame frameNum="127" adm2="0.897333" motion2="6.03259" ms_ssim="0.942072" psnr="31.7998" ssim="0.898137" vif_scale0="0.316819" vif_scale1="0.652754" vif_scale2="0.766261" vif_scale3="0.8421" vmaf="63.8683" />
		<frame frameNum="128" adm2="0.922298" motion2="6.03259" ms_ssim="0.963391" psnr="33.6068" ssim="0.931982" vif_scale0="0.380516" vif_scale1="0.757655" vif_scale2="0.862211" vif_scale3="0.918528" vmaf="76.582" />
		<frame frameNum="129" adm2="0.920934" motion2="6.14852" ms_ssim="0.96037" psnr="33.3742" ssim="0.928019" vif_scale0="0.370005" vif_scale1="0.735416" vif_scale2="0.841382" vif_scale3="0.900935" vmaf="74.5216" />
		<frame frameNum="130" adm2="0.913043" motion2="6.26183" ms_ssim="0.956296" psnr="33.022" ssim="0.920314" vif_scale0="0.353607" vif_scale1="0.702979" vif_scale2="0.812296" vif_scale3="0.877862" vmaf="70.6297" />
		<frame frameNum="131" adm2="0.906611" motion2="6.26183" ms_ssim="0.954399" psnr="32.9629" ssim="0.917893" vif_scale0="0.347998" vif_scale1="0.695582" vif_scale2="0.805769" vif_scale3="0.871018" vmaf="68.7061" />
		<frame frameNum="132" adm2="0.900307" motion2="6.253" ms_ssim="0.950358" psnr="32.6194" ssim="0.911846" vif_scale0="0.335487" vif_scale1="0.6731" vif_scale2="0.783594" vif_scale3="0.852464" vmaf="65.662" />
		<frame frameNum="133" adm2="0.899337" motion2="6.23896" ms_ssim="0.951889" psnr="32.7732" ssim="0.913436" vif_scale0="0.339244" vif_scale1="0.679313" vif_scale2="0.789556" vif_scale3="0.858574" vmaf="65.9958" />
		<frame frameNum="134" adm2="0.89719" motion2="6.13426" ms_ssim="0.95074" psnr="32.6437" ssim="0.912879" vif_scale0="0.335275" vif_scale1="0.675385" vif_scale2="0.786734" vif_scale3="0.856605" vmaf="65.2839" />
		<frame frameNum="135" adm2="0.891226" motion2="6.13426" ms_ssim="0.947088" psnr="32.2577" ssim="0.905864" vif_scale0="0.324095" vif_scale1="0.654992" vif_scale2="0.768259" vif_scale3="0.842264" vmaf="62.7896" />
		<frame frameNum="136" adm2="0.889528" motion2="6.64581" ms_ssim="0.945189" psnr="32.1598" ssim="0.904826" vif_scale0="0.324665" vif_scale1="0.650677" vif_scale2="0.763168" vif_scale3="0.83532" vmaf="62.3981" />
		<frame frameNum="137" adm2="0.885101" motion2="6.97687" ms_ssim="0.944858" psnr="32.0292" ssim="0.902698" vif_scale0="0.322893" vif_scale1="0.649349" vif_scale2="0.760959" vif_scale3="0.836258" vmaf="61.8809" />
		<frame frameNum="138" adm2="0.886413" motion2="7.58123" ms_ssim="0.944521" psnr="32.0299" ssim="0.903933" vif_scale0="0.328741" vif_scale1="0.651177" vif_scale2="0.761573" vif_scale3="0.833934" vmaf="62.5711" />
		<frame frameNum="139" adm2="0.890794" motion2="8.33734" ms_ssim="0.94439" psnr="31.966" ssim="0.901106" vif_scale0="0.328948" vif_scale1="0.649603" vif_scale2="0.762545" vif_scale3="0.834102" vmaf="64.2482" />
		<frame frameNum="140" adm2="0.882937" motion2="8.09961" ms_ssim="0.942079" psnr="31.9016" ssim="0.898282" vif_scale0="0.324889" vif_scale1="0.64205" vif_scale2="0.757226" vif_scale3="0.829898" vmaf="62.122" />
		<frame frameNum="141" adm2="0.877287" motion2="7.98764" ms_ssim="0.936117" psnr="31.4692" ssim="0.889354" vif_scale0="0.312983" vif_scale1="0.618445" vif_scale2="0.731964" vif_scale3="0.807797" vmaf="59.0535" />
		<frame frameNum="142" adm2="0.878108" motion2="7.04206" ms_ssim="0.934666" psnr="31.4453" ssim="0.886646" vif_scale0="0.308546" vif_scale1="0.614404" vif_scale2="0.730005" vif_scale3="0.808632" vmaf="58.3408" />
		<frame frameNum="143" adm2="0.869467" motion2="6.35429" ms_ssim="0.930086" psnr="31.1514" ssim="0.879505" vif_scale0="0.293534" vif_scale1="0.600596" vif_scale2="0.718578" vif_scale3="0.79899" vmaf="55.3175" />
		<frame frameNum="144" adm2="0.913118" motion2="6.35429" ms_ssim="0.95708" psnr="33.2161" ssim="0.920809" vif_scale0="0.358241" vif_scale1="0.717607" vif_scale2="0.830226" vif_scale3="0.892096" vmaf="72.2565" />
		<frame frameNum="145" adm2="0.908865" motion2="6.98423" ms_ssim="0.954402" psnr="32.9864" ssim="0.917549" vif_scale0="0.351854" vif_scale1="0.698551" vif_scale2="0.812678" vif_scale3="0.879237" vmaf="70.6866" />
		<frame frameNum="146" adm2="0.901879" motion2="6.61185" ms_ssim="0.950388" psnr="32.5054" ssim="0.911012" vif_scale0="0.336938" vif_scale1="0.678603" vif_scale2="0.791289" vif_scale3="0.860998" vmaf="67.1254" />
		<frame frameNum="147" adm2="0.903519" motion2="6.61185" ms_ssim="0.951242" psnr="32.66" ssim="0.91185" vif_scale0="0.337673" vif_scale1="0.686288" vif_scale2="0.800129" vif_scale3="0.870202" vmaf="68.3137" />
		<frame frameNum="148" adm2="0.898915" motion2="7.17585" ms_ssim="0.945799" psnr="32.2486" ssim="0.904139" vif_scale0="0.324799" vif_scale1="0.653889" vif_scale2="0.767138" vif_scale3="0.840187" vmaf="65.2018" />
		<frame frameNum="149" adm2="0.897854" motion2="7.07571" ms_ssim="0.946248" psnr="32.2861" ssim="0.904014" vif_scale0="0.324378" vif_scale1="0.663532" vif_scale2="0.77866" vif_scale3="0.851517" vmaf="65.9246" />
		<frame frameNum="150" adm2="0.887759" motion2="7.07571" ms_ssim="0.942182" psnr="31.9924" ssim="0.898151" vif_scale0="0.315489" vif_scale1="0.643672" vif_scale2="0.758579" vif_scale3="0.832852" vmaf="62.2923" />
		<frame frameNum="151" adm2="0.887436" motion2="7.77306" ms_ssim="0.941732" psnr="31.8853" ssim="0.897359" vif_scale0="0.313579" vif_scale1="0.639436" vif_scale2="0.755355" vif_scale3="0.830074" vmaf="62.7002" />
		<frame frameNum="152" adm2="0.882169" motion2="7.90971" ms_ssim="0.936271" psnr="31.6206" ssim="0.88903" vif_scale0="0.301508" vif_scale1="0.614499" vif_scale2="0.729347" vif_scale3="0.807066" vmaf="59.8918" />
		<frame frameNum="153" adm2="0.883377" motion2="7.89941" ms_ssim="0.938338" psnr="31.8329" ssim="0.890902" vif_scale0="0.308595" vif_scale1="0.625902" vif_scale2="0.741799" vif_scale3="0.820373" vmaf="61.1693" />
		<frame frameNum="154" adm2="0.881354" motion2="7.52904" ms_ssim="0.935069" psnr="31.579" ssim="0.88618" vif_scale0="0.303092" vif_scale1="0.614666" vif_scale2="0.728555" vif_scale3="0.806311" vmaf="59.2792" />
		<frame frameNum="155" adm2="0.880095" motion2="7.51082" ms_ssim="0.937377" psnr="31.8021" ssim="0.88927" vif_scale0="0.3082" vif_scale1="0.626276" vif_scale2="0.742173" vif_scale3="0.8205" vmaf="60.1616" />
		<frame frameNum="156" adm2="0.880006" motion2="7.51082" ms_ssim="0.934066" psnr="31.4911" ssim="0.884201" vif_scale0="0.300803" vif_scale1="0.608872" vif_scale2="0.724957" vif_scale3="0.808099" vmaf="59.0992" />
		<frame frameNum="157" adm2="0.882816" motion2="8.05149" ms_ssim="0.938869" psnr="31.7949" ssim="0.89237" vif_scale0="0.31569" vif_scale1="0.628415" vif_scale2="0.743068" vif_scale3="0.822692" vmaf="61.3449" />
		<frame frameNum="158" adm2="0.872404" motion2="7.78545" ms_ssim="0.935083" psnr="31.5415" ssim="0.886566" vif_scale0="0.307817" vif_scale1="0.610325" vif_scale2="0.724821" vif_scale3="0.805347" vmaf="57.6796" />
		<frame frameNum="159" adm2="0.870859" motion2="7.78545" ms_ssim="0.93422" psnr="31.4618" ssim="0.886596" vif_scale0="0.308942" vif_scale1="0.606358" vif_scale2="0.717458" vif_scale3="0.795503" vmaf="56.6038" />
		<frame frameNum="160" adm2="0.915217" motion2="7.74201" ms_ssim="0.960703" psnr="33.5471" ssim="0.926609" vif_scale0="0.374871" vif_scale1="0.726049" vif_scale2="0.832932" vif_scale3="0.893257" vmaf="74.2127" />
		<frame frameNum="161" adm2="0.915563" motion2="7.74201" ms_ssim="0.957793" psnr="33.2867" ssim="0.923148" vif_scale0="0.367274" vif_scale1="0.704742" vif_scale2="0.812644" vif_scale3="0.875752" vmaf="72.4904" />
		<frame frameNum="162" adm2="0.905142" motion2="7.89478" ms_ssim="0.95183" psnr="32.7016" ssim="0.913807" vif_scale0="0.349856" vif_scale1="0.667571" vif_scale2="0.776871" vif_scale3="0.847852" vmaf="67.7843" />
		<frame frameNum="163" adm2="0.900385" motion2="8.03169" ms_ssim="0.953434" psnr="32.872" ssim="0.915485" vif_scale0="0.356892" vif_scale1="0.676824" vif_scale2="0.785912" vif_scale3="0.854445" vmaf="67.6112" />
		<frame frameNum="164" adm2="0.891975" motion2="7.87614" ms_ssim="0.948562" psnr="32.5146" ssim="0.909158" vif_scale0="0.345404" vif_scale1="0.655877" vif_scale2="0.764559" vif_scale3="0.835013" vmaf="64.0253" />
		<frame frameNum="165" adm2="0.8918" motion2="7.45168" ms_ssim="0.950766" psnr="32.8046" ssim="0.912062" vif_scale0="0.350494" vif_scale1="0.668975" vif_scale2="0.777872" vif_scale3="0.847303" vmaf="64.6577" />
		<frame frameNum="166" adm2="0.888549" motion2="7.03216" ms_ssim="0.945454" psnr="32.4478" ssim="0.904496" vif_scale0="0.337833" vif_scale1="0.645475" vif_scale2="0.754213" vif_scale3="0.827086" vmaf="61.7891" />
		<frame frameNum="167" adm2="0.890844" motion2="6.83577" ms_ssim="0.945313" psnr="32.5013" ssim="0.90491" vif_scale0="0.33606" vif_scale1="0.650374" vif_scale2="0.760949" vif_scale3="0.832172" vmaf="62.5348" />
		<frame frameNum="168" adm2="0.880296" motion2="6.82718" ms_ssim="0.941288" psnr="32.2329" ssim="0.898091" vif_scale0="0.323527" vif_scale1="0.633339" vif_scale2="0.745814" vif_scale3="0.823219" vmaf="59.6569" />
		<frame frameNum="169" adm2="0.889071" motion2="6.69626" ms_ssim="0.946645" psnr="32.7155" ssim="0.905464" vif_scale0="0.336487" vif_scale1="0.657536" vif_scale2="0.767624" vif_scale3="0.841596" vmaf="62.8023" />
		<frame frameNum="170" adm2="0.87536" motion2="6.69626" ms_ssim="0.941157" psnr="32.1867" ssim="0.897999" vif_scale0="0.320345" vif_scale1="0.632301" vif_scale2="0.744568" vif_scale3="0.819347" vmaf="58.3008" />
		<frame frameNum="171" adm2="0.887005" motion2="6.72132" ms_ssim="0.947508" psnr="32.5665" ssim="0.90646" vif_scale0="0.337707" vif_scale1="0.663874" vif_scale2="0.774502" vif_scale3="0.847694" vmaf="62.9765" />
		<frame frameNum="172" adm2="0.880099" motion2="7.17135" ms_ssim="0.942977" psnr="32.1326" ssim="0.899203" vif_scale0="0.327794" vif_scale1="0.642423" vif_scale2="0.754156" vif_scale3="0.830601" vmaf="60.5766" />
		<frame frameNum="173" adm2="0.889182" motion2="6.94309" ms_ssim="0.944364" psnr="32.2763" ssim="0.902115" vif_scale0="0.331763" vif_scale1="0.650488" vif_scale2="0.761488" vif_scale3="0.835147" vmaf="62.5461" />
		<frame frameNum="174" adm2="0.888151" motion2="6.71341" ms_ssim="0.941358" psnr="32.0208" ssim="0.897616" vif_scale0="0.322138" vif_scale1="0.63536" vif_scale2="0.747427" vif_scale3="0.821545" vmaf="60.9925" />
		<frame frameNum="175" adm2="0.895031" motion2="6.71341" ms_ssim="0.946882" psnr="32.4816" ssim="0.905036" vif_scale0="0.338135" vif_scale1="0.664217" vif_scale2="0.777486" vif_scale3="0.849921" vmaf="64.7965" />
		<frame frameNum="176" adm2="0.925335" motion2="6.78476" ms_ssim="0.966626" psnr="34.2543" ssim="0.937207" vif_scale0="0.401285" vif_scale1="0.761066" vif_scale2="0.860338" vif_scale3="0.915536" vmaf="77.6576" />
		<frame frameNum="177" adm2="0.920513" motion2="6.74514" ms_ssim="0.964259" psnr="34.0092" ssim="0.934025" vif_scale0="0.392759" vif_scale1="0.740515" vif_scale2="0.840811" vif_scale3="0.901185" vmaf="74.9806" />
		<frame frameNum="178" adm2="0.915746" motion2="6.69922" ms_ssim="0.961613" psnr="33.724" ssim="0.929456" vif_scale0="0.383303" vif_scale1="0.721573" vif_scale2="0.82279" vif_scale3="0.887156" vmaf="72.4465" />
		<frame frameNum="179" adm2="0.914885" motion2="6.15912" ms_ssim="0.960056" psnr="33.6651" ssim="0.92706" vif_scale0="0.381086" vif_scale1="0.717554" vif_scale2="0.818028" vif_scale3="0.880852" vmaf="71.1187" />
		<frame frameNum="180" adm2="0.914409" motion2="5.91334" ms_ssim="0.95902" psnr="33.604" ssim="0.925268" vif_scale0="0.375297" vif_scale1="0.71244" vif_scale2="0.815299" vif_scale3="0.881248" vmaf="70.7486" />
		<frame frameNum="181" adm2="0.917781" motion2="5.44625" ms_ssim="0.958658" psnr="33.7481" ssim="0.924788" vif_scale0="0.373529" vif_scale1="0.712561" vif_scale2="0.815987" vif_scale3="0.882739" vmaf="71.0703" />
		<frame frameNum="182" adm2="0.909363" motion2="5.22741" ms_ssim="0.957096" psnr="33.4919" ssim="0.921973" vif_scale0="0.361514" vif_scale1="0.700865" vif_scale2="0.805677" vif_scale3="0.87387" vmaf="68.2843" />
		<frame frameNum="183" adm2="0.90995" motion2="5.19856" ms_ssim="0.95911" psnr="33.6559" ssim="0.92523" vif_scale0="0.36591" vif_scale1="0.71432" vif_scale2="0.818453" vif_scale3="0.882874" vmaf="69.3257" />
		<frame frameNum="184" adm2="0.906538" motion2="5.0849" ms_ssim="0.956792" psnr="33.3917" ssim="0.921086" vif_scale0="0.355832" vif_scale1="0.698324" vif_scale2="0.804758" vif_scale3="0.871423" vmaf="67.4023" />
		<frame frameNum="185" adm2="0.912736" motion2="5.0849" ms_ssim="0.960115" psnr="33.805" ssim="0.926814" vif_scale0="0.371957" vif_scale1="0.727486" vif_scale2="0.831986" vif_scale3="0.894461" vmaf="70.958" />
		<frame frameNum="186" adm2="0.905311" motion2="4.91296" ms_ssim="0.956684" psnr="33.4243" ssim="0.921449" vif_scale0="0.354959" vif_scale1="0.703233" vif_scale2="0.810145" vif_scale3="0.878602" vmaf="67.6233" />
		<frame frameNum="187" adm2="0.909793" motion2="4.58126" ms_ssim="0.960193" psnr="33.8034" ssim="0.927589" vif_scale0="0.370595" vif_scale1="0.726754" vif_scale2="0.831459" vif_scale3="0.895412" vmaf="69.8793" />
		<frame frameNum="188" adm2="0.901832" motion2="4.26234" ms_ssim="0.956576" psnr="33.4367" ssim="0.92187" vif_scale0="0.354086" vif_scale1="0.703572" vif_scale2="0.810038" vif_scale3="0.876943" vmaf="66.1128" />
		<frame frameNum="189" adm2="0.910703" motion2="4.13581" ms_ssim="0.959983" psnr="33.7521" ssim="0.927413" vif_scale0="0.368766" vif_scale1="0.729408" vif_scale2="0.833611" vif_scale3="0.896389" vmaf="69.7184" />
		<frame frameNum="190" adm2="0.905834" motion2="3.61481" ms_ssim="0.956915" psnr="33.3908" ssim="0.922104" vif_scale0="0.354066" vif_scale1="0.708154" vif_scale2="0.815304" vif_scale3="0.882509" vmaf="66.7581" />
		<frame frameNum="191" adm2="0.911653" motion2="3.59475" ms_ssim="0.959358" psnr="33.6951" ssim="0.925727" vif_scale0="0.367246" vif_scale1="0.727325" vif_scale2="0.832162" vif_scale3="0.895641" vmaf="69.2397" />
		<frame frameNum="192" adm2="0.937636" motion2="3.41975" ms_ssim="0.973057" psnr="35.2867" ssim="0.948943" vif_scale0="0.426362" vif_scale1="0.80423" vif_scale2="0.891034" vif_scale3="0.934167" vmaf="78.8535" />
		<frame frameNum="193" adm2="0.933796" motion2="3.10451" ms_ssim="0.971803" psnr="35.0907" ssim="0.947578" vif_scale0="0.41823" vif_scale1="0.79041" vif_scale2="0.880813" vif_scale3="0.927942" vmaf="76.9034" />
		<frame frameNum="194" adm2="0.93271" motion2="2.95701" ms_ssim="0.971051" psnr="34.9824" ssim="0.946854" vif_scale0="0.414431" vif_scale1="0.786604" vif_scale2="0.876782" vif_scale3="0.923091" vmaf="76.0204" />
		<frame frameNum="195" adm2="0.940478" motion2="2.95701" ms_ssim="0.973001" psnr="35.356" ssim="0.950207" vif_scale0="0.429172" vif_scale1="0.806445" vif_scale2="0.892315" vif_scale3="0.933784" vmaf="78.9278" />
		<frame frameNum="196" adm2="0.93483" motion2="3.34571" ms_ssim="0.971732" psnr="35.04" ssim="0.947529" vif_scale0="0.42045" vif_scale1="0.792437" vif_scale2="0.880831" vif_scale3="0.925468" vmaf="77.1914" />
		<frame frameNum="197" adm2="0.935744" motion2="3.50494" ms_ssim="0.971919" psnr="35.1224" ssim="0.947534" vif_scale0="0.425341" vif_scale1="0.79604" vif_scale2="0.88366" vif_scale3="0.927549" vmaf="77.7996" />
		<frame frameNum="198" adm2="0.926886" motion2="3.435" ms_ssim="0.969568" psnr="34.7113" ssim="0.943789" vif_scale0="0.411123" vif_scale1="0.773908" vif_scale2="0.865772" vif_scale3="0.915917" vmaf="74.4672" />
		<frame frameNum="199" adm2="0.92577" motion2="3.39252" ms_ssim="0.971342" psnr="34.9995" ssim="0.946874" vif_scale0="0.423815" vif_scale1="0.789842" vif_scale2="0.878012" vif_scale3="0.923981" vmaf="75.1466" />
		<frame frameNum="200" adm2="0.920809" motion2="3.33713" ms_ssim="0.969392" psnr="34.7887" ssim="0.943534" vif_scale0="0.412244" vif_scale1="0.773897" vif_scale2="0.866414" vif_scale3="0.916776" vmaf="73.19" />
		<frame frameNum="201" adm2="0.922108" motion2="3.24127" ms_ssim="0.969243" psnr="34.8329" ssim="0.942946" vif_scale0="0.411906" vif_scale1="0.776881" vif_scale2="0.868969" vif_scale3="0.917156" vmaf="73.4615" />
		<frame frameNum="202" adm2="0.920055" motion2="3.24127" ms_ssim="0.96719" psnr="34.6022" ssim="0.93968" vif_scale0="0.40185" vif_scale1="0.762836" vif_scale2="0.856707" vif_scale3="0.907691" vmaf="71.9872" />
		<frame frameNum="203" adm2="0.926085" motion2="3.38945" ms_ssim="0.970216" psnr="35.0309" ssim="0.944583" vif_scale0="0.41741" vif_scale1="0.785237" vif_scale2="0.874471" vif_scale3="0.921736" vmaf="74.9433" />
		<frame frameNum="204" adm2="0.923314" motion2="3.39452" ms_ssim="0.968519" psnr="34.7829" ssim="0.941822" vif_scale0="0.40549" vif_scale1="0.767653" vif_scale2="0.860998" vif_scale3="0.912394" vmaf="73.2952" />
		<frame frameNum="205" adm2="0.926384" motion2="3.42487" ms_ssim="0.970685" psnr="35.0851" ssim="0.945529" vif_scale0="0.419539" vif_scale1="0.786698" vif_scale2="0.875916" vif_scale3="0.924636" vmaf="75.304" />
		<frame frameNum="206" adm2="0.92263" motion2="3.46612" ms_ssim="0.968062" psnr="34.7105" ssim="0.941252" vif_scale0="0.400846" vif_scale1="0.764335" vif_scale2="0.858112" vif_scale3="0.910179" vmaf="72.9955" />
		<frame frameNum="207" adm2="0.915461" motion2="3.57659" ms_ssim="0.96797" psnr="34.688" ssim="0.941351" vif_scale0="0.403191" vif_scale1="0.768195" vif_scale2="0.860134" vif_scale3="0.910524" vmaf="71.7192" />
		<frame frameNum="208" adm2="0.948174" motion2="3.47862" ms_ssim="0.980087" psnr="36.7143" ssim="0.962217" vif_scale0="0.48476" vif_scale1="0.852254" vif_scale2="0.923453" vif_scale3="0.95755" vmaf="83.9938" />
		<frame frameNum="209" adm2="0.947079" motion2="3.47862" ms_ssim="0.979222" psnr="36.4726" ssim="0.960682" vif_scale0="0.477357" vif_scale1="0.842749" vif_scale2="0.916571" vif_scale3="0.951871" vmaf="83.0676" />
		<frame frameNum="210" adm2="0.940543" motion2="3.5883" ms_ssim="0.977442" psnr="36.0613" ssim="0.958006" vif_scale0="0.464568" vif_scale1="0.824938" vif_scale2="0.902789" vif_scale3="0.941947" vmaf="80.5606" />
		<frame frameNum="211" adm2="0.943351" motion2="3.89606" ms_ssim="0.978075" psnr="36.1367" ssim="0.959326" vif_scale0="0.469635" vif_scale1="0.832116" vif_scale2="0.908773" vif_scale3="0.946421" vmaf="82.06" />
		<frame frameNum="212" adm2="0.937205" motion2="4.09141" ms_ssim="0.976128" psnr="35.6692" ssim="0.95635" vif_scale0="0.455314" vif_scale1="0.813302" vif_scale2="0.894426" vif_scale3="0.936636" vmaf="79.7474" />
		<frame frameNum="213" adm2="0.936021" motion2="4.31655" ms_ssim="0.974665" psnr="35.5207" ssim="0.953943" vif_scale0="0.448508" vif_scale1="0.802776" vif_scale2="0.885827" vif_scale3="0.930264" vmaf="78.981" />
		<frame frameNum="214" adm2="0.934882" motion2="3.86983" ms_ssim="0.973808" psnr="35.4348" ssim="0.952703" vif_scale0="0.443197" vif_scale1="0.795988" vif_scale2="0.879273" vif_scale3="0.924695" vmaf="77.6027" />
		<frame frameNum="215" adm2="0.935065" motion2="3.824" ms_ssim="0.972372" psnr="35.3198" ssim="0.951022" vif_scale0="0.437848" vif_scale1="0.786559" vif_scale2="0.870354" vif_scale3="0.918085" vmaf="76.8023" />
		<frame frameNum="216" adm2="0.92876" motion2="3.824" ms_ssim="0.9717" psnr="35.1875" ssim="0.949352" vif_scale0="0.430345" vif_scale1="0.779051" vif_scale2="0.865207" vif_scale3="0.914121" vmaf="75.057" />
		<frame frameNum="217" adm2="0.92967" motion2="3.79508" ms_ssim="0.971242" psnr="35.0778" ssim="0.948681" vif_scale0="0.429316" vif_scale1="0.777565" vif_scale2="0.863736" vif_scale3="0.912662" vmaf="75.0589" />
		<frame frameNum="218" adm2="0.920884" motion2="3.79508" ms_ssim="0.966596" psnr="34.5145" ssim="0.941464" vif_scale0="0.407588" vif_scale1="0.752285" vif_scale2="0.843633" vif_scale3="0.895578" vmaf="71.4489" />
		<frame frameNum="219" adm2="0.916861" motion2="3.8174" ms_ssim="0.966372" psnr="34.5431" ssim="0.941486" vif_scale0="0.408943" vif_scale1="0.751446" vif_scale2="0.840671" vif_scale3="0.892854" vmaf="70.3472" />
		<frame frameNum="220" adm2="0.919006" motion2="3.8174" ms_ssim="0.965238" psnr="34.4672" ssim="0.939604" vif_scale0="0.40504" vif_scale1="0.743142" vif_scale2="0.833974" vif_scale3="0.887708" vmaf="70.2372" />
		<frame frameNum="221" adm2="0.916213" motion2="4.13878" ms_ssim="0.963837" psnr="34.4008" ssim="0.937274" vif_scale0="0.401855" vif_scale1="0.73787" vif_scale2="0.828006" vif_scale3="0.884009" vmaf="69.5874" />
		<frame frameNum="222" adm2="0.912165" motion2="3.90857" ms_ssim="0.9628" psnr="34.2296" ssim="0.935136" vif_scale0="0.394837" vif_scale1="0.729404" vif_scale2="0.821894" vif_scale3="0.879251" vmaf="68.0403" />
		<frame frameNum="223" adm2="0.904328" motion2="3.79197" ms_ssim="0.958574" psnr="33.6893" ssim="0.927838" vif_scale0="0.375448" vif_scale1="0.70565" vif_scale2="0.802303" vif_scale3="0.864117" vmaf="64.8522" />
		<frame frameNum="224" adm2="0.935236" motion2="3.59535" ms_ssim="0.972809" psnr="35.4078" ssim="0.949945" vif_scale0="0.432032" vif_scale1="0.799833" vif_scale2="0.886973" vif_scale3="0.93254" vmaf="78.2694" />
		<frame frameNum="225" adm2="0.933258" motion2="3.59535" ms_ssim="0.971008" psnr="35.1451" ssim="0.947136" vif_scale0="0.423544" vif_scale1="0.787611" vif_scale2="0.87647" vif_scale3="0.924553" vmaf="76.9197" />
		<frame frameNum="226" adm2="0.928912" motion2="3.76439" ms_ssim="0.968095" psnr="34.6306" ssim="0.942978" vif_scale0="0.411888" vif_scale1="0.763987" vif_scale2="0.855556" vif_scale3="0.909299" vmaf="74.4279" />
		<frame frameNum="227" adm2="0.923829" motion2="3.93731" ms_ssim="0.966982" psnr="34.474" ssim="0.941485" vif_scale0="0.407261" vif_scale1="0.759044" vif_scale2="0.852768" vif_scale3="0.906627" vmaf="73.3131" />
		<frame frameNum="228" adm2="0.924075" motion2="4.16357" ms_ssim="0.963917" psnr="34.0773" ssim="0.93722" vif_scale0="0.393213" vif_scale1="0.73997" vif_scale2="0.835016" vif_scale3="0.889825" vmaf="71.899" />
		<frame frameNum="229" adm2="0.922655" motion2="4.29196" ms_ssim="0.963703" psnr="33.9863" ssim="0.93543" vif_scale0="0.391025" vif_scale1="0.731944" vif_scale2="0.829209" vif_scale3="0.887823" vmaf="71.4563" />
		<frame frameNum="230" adm2="0.91402" motion2="4.55726" ms_ssim="0.960905" psnr="33.513" ssim="0.93125" vif_scale0="0.379298" vif_scale1="0.715954" vif_scale2="0.81513" vif_scale3="0.875143" vmaf="68.7434" />
		<frame frameNum="231" adm2="0.910808" motion2="4.8647" ms_ssim="0.960358" psnr="33.3425" ssim="0.929987" vif_scale0="0.376513" vif_scale1="0.71121" vif_scale2="0.812182" vif_scale3="0.874131" vmaf="68.2967" />
		<frame frameNum="232" adm2="0.905162" motion2="4.8647" ms_ssim="0.955133" psnr="32.6901" ssim="0.922009" vif_scale0="0.356147" vif_scale1="0.68259" vif_scale2="0.785029" vif_scale3="0.850992" vmaf="64.9632" />
		<frame frameNum="233" adm2="0.899" motion2="5.10533" ms_ssim="0.95611" psnr="32.7722" ssim="0.923219" vif_scale0="0.355832" vif_scale1="0.684723" vif_scale2="0.788773" vif_scale3="0.855131" vmaf="64.375" />
		<frame frameNum="234" adm2="0.899559" motion2="5.41418" ms_ssim="0.955602" psnr="32.7873" ssim="0.922668" vif_scale0="0.355783" vif_scale1="0.68399" vif_scale2="0.788379" vif_scale3="0.854628" vmaf="64.7705" />
		<frame frameNum="235" adm2="0.891682" motion2="5.79551" ms_ssim="0.953282" psnr="32.6738" ssim="0.919161" vif_scale0="0.350062" vif_scale1="0.673347" vif_scale2="0.777581" vif_scale3="0.846626" vmaf="62.8323" />
		<frame frameNum="236" adm2="0.893613" motion2="6.68663" ms_ssim="0.951087" psnr="32.4159" ssim="0.915312" vif_scale0="0.346758" vif_scale1="0.661085" vif_scale2="0.764936" vif_scale3="0.832655" vmaf="62.9319" />
		<frame frameNum="237" adm2="0.873941" motion2="7.25686" ms_ssim="0.943721" psnr="31.7449" ssim="0.904193" vif_scale0="0.325916" vif_scale1="0.625492" vif_scale2="0.730612" vif_scale3="0.802882" vmaf="57.1875" />
		<frame frameNum="238" adm2="0.873092" motion2="7.41748" ms_ssim="0.944583" psnr="31.8495" ssim="0.905278" vif_scale0="0.330076" vif_scale1="0.633002" vif_scale2="0.739217" vif_scale3="0.81084" vmaf="57.8319" />
		<frame frameNum="239" adm2="0.867241" motion2="7.47853" ms_ssim="0.941382" psnr="31.6079" ssim="0.899656" vif_scale0="0.320244" vif_scale1="0.611598" vif_scale2="0.71991" vif_scale3="0.797407" vmaf="55.6785" />
		<frame frameNum="240" adm2="0.922405" motion2="7.35366" ms_ssim="0.968469" psnr="34.3578" ssim="0.941246" vif_scale0="0.410832" vif_scale1="0.76266" vif_scale2="0.862826" vif_scale3="0.917446" vmaf="77.865" />
		<frame frameNum="241" adm2="0.922363" motion2="7.03315" ms_ssim="0.96584" psnr="34.0172" ssim="0.9371" vif_scale0="0.399405" vif_scale1="0.741116" vif_scale2="0.841969" vif_scale3="0.899736" vmaf="75.5837" />
		<frame frameNum="242" adm2="0.909293" motion2="6.77448" ms_ssim="0.960306" psnr="33.2338" ssim="0.928545" vif_scale0="0.375616" vif_scale1="0.704036" vif_scale2="0.809375" vif_scale3="0.87291" vmaf="69.8891" />
		<frame frameNum="243" adm2="0.898476" motion2="6.77448" ms_ssim="0.954278" psnr="32.5417" ssim="0.91869" vif_scale0="0.354735" vif_scale1="0.671798" vif_scale2="0.778525" vif_scale3="0.846286" vmaf="65.2003" />
		<frame frameNum="244" adm2="0.893187" motion2="6.81684" ms_ssim="0.950561" psnr="32.1587" ssim="0.912148" vif_scale0="0.342506" vif_scale1="0.654847" vif_scale2="0.763985" vif_scale3="0.837607" vmaf="63.3645" />
		<frame frameNum="245" adm2="0.885563" motion2="6.81684" ms_ssim="0.944459" psnr="31.6128" ssim="0.903134" vif_scale0="0.327351" vif_scale1="0.628544" vif_scale2="0.736662" vif_scale3="0.811394" vmaf="59.6769" />
		<frame frameNum="246" adm2="0.886225" motion2="6.88901" ms_ssim="0.94211" psnr="31.3878" ssim="0.898805" vif_scale0="0.321989" vif_scale1="0.619322" vif_scale2="0.727895" vif_scale3="0.805138" vmaf="59.3585" />
		<frame frameNum="247" adm2="0.882004" motion2="6.97811" ms_ssim="0.941544" psnr="31.2957" ssim="0.897753" vif_scale0="0.319912" vif_scale1="0.61725" vif_scale2="0.728164" vif_scale3="0.805507" vmaf="58.6957" />
		<frame frameNum="248" adm2="0.876451" motion2="6.95621" ms_ssim="0.938327" psnr="31.0358" ssim="0.892645" vif_scale0="0.311602" vif_scale1="0.603736" vif_scale2="0.716359" vif_scale3="0.796184" vmaf="56.8937" />
		<frame frameNum="249" adm2="0.859365" motion2="6.95621" ms_ssim="0.927497" psnr="30.3399" ssim="0.877101" vif_scale0="0.290037" vif_scale1="0.567205" vif_scale2="0.678442" vif_scale3="0.758605" vmaf="51.0097" />
	</frames>
</VMAF>
